<?xml version="1.0" encoding="utf-8"?>
<Th06SpellCardData>
  <Information>
    <Game>東方紅魔郷　～ the Embodiment of Scarlet Devil.</Game>
    <DataKind>東方紅魔郷スペルカードデータファイル</DataKind>
    <Author>稲凪茉白</Author>
    <Copyright>Copyright (c) 2022 Mashiro Inagi</Copyright>
    <Version>1.1</Version>
  </Information>
  <SpellCard ID="1">
    <Name>月符「ムーンライトレイ」</Name>
    <Enemy>ルーミア</Enemy>
    <Place>1面道中</Place>
    <Level>Hard, Lunatic</Level>
  </SpellCard>
  <SpellCard ID="2">
    <Name>夜符「ナイトバード」</Name>
    <Enemy>ルーミア</Enemy>
    <Place>1面ボス</Place>
    <Level>ALL Level</Level>
  </SpellCard>
  <SpellCard ID="3">
    <Name>闇符「ディマーケイション」</Name>
    <Enemy>ルーミア</Enemy>
    <Place>1面ボス</Place>
    <Level>ALL Level</Level>
  </SpellCard>
  <SpellCard ID="4">
    <Name>氷符「アイシクルフォール」</Name>
    <Enemy>チルノ</Enemy>
    <Place>2面ボス</Place>
    <Level>Easy, Normal</Level>
  </SpellCard>
  <SpellCard ID="5">
    <Name>雹符「ヘイルストーム」</Name>
    <Enemy>チルノ</Enemy>
    <Place>2面ボス</Place>
    <Level>Hard, Lunatic</Level>
  </SpellCard>
  <SpellCard ID="6">
    <Name>凍符「パーフェクトフリーズ」</Name>
    <Enemy>チルノ</Enemy>
    <Place>2面ボス</Place>
    <Level>ALL Level</Level>
  </SpellCard>
  <SpellCard ID="7">
    <Name>雪符「ダイアモンドブリザード」</Name>
    <Enemy>チルノ</Enemy>
    <Place>2面ボス</Place>
    <Level>Normal, Hard, Lunatic</Level>
  </SpellCard>
  <SpellCard ID="8">
    <Name>華符「芳華絢爛」</Name>
    <Enemy>紅美鈴</Enemy>
    <Place>3面道中</Place>
    <Level>Easy, Normal</Level>
  </SpellCard>
  <SpellCard ID="9">
    <Name>華符「セラギネラ９」</Name>
    <Enemy>紅美鈴</Enemy>
    <Place>3面道中</Place>
    <Level>Hard, Lunatic</Level>
  </SpellCard>
  <SpellCard ID="10">
    <Name>虹符「彩虹の風鈴」</Name>
    <Enemy>紅美鈴</Enemy>
    <Place>3面ボス</Place>
    <Level>ALL Level</Level>
  </SpellCard>
  <SpellCard ID="11">
    <Name>幻符「華想夢葛」</Name>
    <Enemy>紅美鈴</Enemy>
    <Place>3面ボス</Place>
    <Level>Hard, Lunatic</Level>
  </SpellCard>
  <SpellCard ID="12">
    <Name>彩符「彩雨」</Name>
    <Enemy>紅美鈴</Enemy>
    <Place>3面ボス</Place>
    <Level>Easy, Normal</Level>
  </SpellCard>
  <SpellCard ID="13">
    <Name>彩符「彩光乱舞」</Name>
    <Enemy>紅美鈴</Enemy>
    <Place>3面ボス</Place>
    <Level>Hard, Normal</Level>
  </SpellCard>
  <SpellCard ID="14">
    <Name>彩符「極彩颱風」</Name>
    <Enemy>紅美鈴</Enemy>
    <Place>3面ボス</Place>
    <Level>Normal, Hard, Lunatic</Level>
  </SpellCard>
  <SpellCard ID="15">
    <Name>火符「アグニシャイン」</Name>
    <Enemy>パチュリー・ノーレッジ</Enemy>
    <Place>4面ボス</Place>
    <Level>Easy(霊符霊夢), Normal(霊符霊夢)</Level>
  </SpellCard>
  <SpellCard ID="16">
    <Name>水符「プリンセスウンディネ」</Name>
    <Enemy>パチュリー・ノーレッジ</Enemy>
    <Place>4面ボス</Place>
    <Level>Easy(夢符霊夢), Normal(夢符霊夢)</Level>
  </SpellCard>
  <SpellCard ID="17">
    <Name>木符「シルフィホルン」</Name>
    <Enemy>パチュリー・ノーレッジ</Enemy>
    <Place>4面ボス</Place>
    <Level>Easy(魔符魔理沙), Normal(魔符魔理沙)</Level>
  </SpellCard>
  <SpellCard ID="18">
    <Name>土符「レイジィトリリトン」</Name>
    <Enemy>パチュリー・ノーレッジ</Enemy>
    <Place>4面ボス</Place>
    <Level>Easy(恋符魔理沙), Normal(恋符魔理沙)</Level>
  </SpellCard>
  <SpellCard ID="19">
    <Name>金符「メタルファティーグ」</Name>
    <Enemy>パチュリー・ノーレッジ</Enemy>
    <Place>4面ボス</Place>
    <Level>Normal(恋符魔理沙)</Level>
  </SpellCard>
  <SpellCard ID="20">
    <Name>火符「アグニシャイン上級」</Name>
    <Enemy>パチュリー・ノーレッジ</Enemy>
    <Place>4面ボス</Place>
    <Level>Normal(魔符魔理沙), Hard(霊符霊夢), Lunatic(霊符霊夢)</Level>
  </SpellCard>
  <SpellCard ID="21">
    <Name>木符「シルフィホルン上級」</Name>
    <Enemy>パチュリー・ノーレッジ</Enemy>
    <Place>4面ボス</Place>
    <Level>Normal(夢符霊夢), Hard(魔符魔理沙), Lunatic(魔符魔理沙)</Level>
  </SpellCard>
  <SpellCard ID="22">
    <Name>土符「レイジィトリリトン上級」</Name>
    <Enemy>パチュリー・ノーレッジ</Enemy>
    <Place>4面ボス</Place>
    <Level>Normal(霊符霊夢), Hard(恋符魔理沙), Lunatic(恋符魔理沙)</Level>
  </SpellCard>
  <SpellCard ID="23">
    <Name>火符「アグニレイディアンス」</Name>
    <Enemy>パチュリー・ノーレッジ</Enemy>
    <Place>4面ボス</Place>
    <Level>Hard(魔符魔理沙), Lunatic(魔符魔理沙)</Level>
  </SpellCard>
  <SpellCard ID="24">
    <Name>水符「ベリーインレイク」</Name>
    <Enemy>パチュリー・ノーレッジ</Enemy>
    <Place>4面ボス</Place>
    <Level>Hard(夢符霊夢), Lunatic(夢符霊夢)</Level>
  </SpellCard>
  <SpellCard ID="25">
    <Name>木符「グリーンストーム」</Name>
    <Enemy>パチュリー・ノーレッジ</Enemy>
    <Place>4面ボス</Place>
    <Level>Hard(夢符霊夢), Lunatic(夢符霊夢)</Level>
  </SpellCard>
  <SpellCard ID="26">
    <Name>土符「トリリトンシェイク」</Name>
    <Enemy>パチュリー・ノーレッジ</Enemy>
    <Place>4面ボス</Place>
    <Level>Hard(霊符霊夢), Lunatic(霊符霊夢)</Level>
  </SpellCard>
  <SpellCard ID="27">
    <Name>金符「シルバードラゴン」</Name>
    <Enemy>パチュリー・ノーレッジ</Enemy>
    <Place>4面ボス</Place>
    <Level>Hard(恋符魔理沙), Lunatic(恋符魔理沙)</Level>
  </SpellCard>
  <SpellCard ID="28">
    <Name>火＆土符「ラーヴァクロムレク」</Name>
    <Enemy>パチュリー・ノーレッジ</Enemy>
    <Place>4面ボス</Place>
    <Level>Easy(霊符霊夢), Normal(霊符霊夢), Hard(霊符霊夢, 魔符魔理沙), Lunatic(霊符霊夢, 魔符魔理沙)</Level>
  </SpellCard>
  <SpellCard ID="29">
    <Name>木＆火符「フォレストブレイズ」</Name>
    <Enemy>パチュリー・ノーレッジ</Enemy>
    <Place>4面ボス</Place>
    <Level>Easy(魔符魔理沙), Normal(魔符魔理沙), Hard(霊符霊夢, 魔符魔理沙), Lunatic(霊符霊夢, 魔符魔理沙)</Level>
  </SpellCard>
  <SpellCard ID="30">
    <Name>水＆木符「ウォーターエルフ」</Name>
    <Enemy>パチュリー・ノーレッジ</Enemy>
    <Place>4面ボス</Place>
    <Level>Easy(夢符霊夢), Normal(夢符霊夢, 恋符魔理沙), Hard(夢符霊夢, 魔符魔理沙), Lunatic(夢符霊夢, 魔符魔理沙)</Level>
  </SpellCard>
  <SpellCard ID="31">
    <Name>金＆水符「マーキュリポイズン」</Name>
    <Enemy>パチュリー・ノーレッジ</Enemy>
    <Place>4面ボス</Place>
    <Level>Normal(霊夢), Hard(霊夢, 恋符魔理沙), Lunatic(霊夢, 恋符魔理沙)</Level>
  </SpellCard>
  <SpellCard ID="32">
    <Name>土＆金符「エメラルドメガリス」</Name>
    <Enemy>パチュリー・ノーレッジ</Enemy>
    <Place>4面ボス</Place>
    <Level>Normal(霊夢), Hard(霊夢, 恋符魔理沙), Lunatic(霊夢, 恋符魔理沙)</Level>
  </SpellCard>
  <SpellCard ID="33">
    <Name>奇術「ミスディレクション」</Name>
    <Enemy>十六夜咲夜</Enemy>
    <Place>5面道中</Place>
    <Level>Easy, Normal</Level>
  </SpellCard>
  <SpellCard ID="34">
    <Name>奇術「幻惑ミスディレクション」</Name>
    <Enemy>十六夜咲夜</Enemy>
    <Place>5面道中</Place>
    <Level>Hard, Lunatic</Level>
  </SpellCard>
  <SpellCard ID="35">
    <Name>幻在「クロックコープス」</Name>
    <Enemy>十六夜咲夜</Enemy>
    <Place>5面ボス</Place>
    <Level>Easy, Normal</Level>
  </SpellCard>
  <SpellCard ID="36">
    <Name>幻象「ルナクロック」</Name>
    <Enemy>十六夜咲夜</Enemy>
    <Place>5面ボス</Place>
    <Level>Easy, Normal</Level>
  </SpellCard>
  <SpellCard ID="37">
    <Name>メイド秘技「操りドール」</Name>
    <Enemy>十六夜咲夜</Enemy>
    <Place>5面ボス</Place>
    <Level>Easy, Normal</Level>
  </SpellCard>
  <SpellCard ID="38">
    <Name>幻幽「ジャック・ザ・ルドビレ」</Name>
    <Enemy>十六夜咲夜</Enemy>
    <Place>5面ボス</Place>
    <Level>Hard, Lunatic</Level>
  </SpellCard>
  <SpellCard ID="39">
    <Name>幻世「ザ・ワールド」</Name>
    <Enemy>十六夜咲夜</Enemy>
    <Place>5面ボス</Place>
    <Level>Hard, Lunatic</Level>
  </SpellCard>
  <SpellCard ID="40">
    <Name>メイド秘技「殺人ドール」</Name>
    <Enemy>十六夜咲夜</Enemy>
    <Place>5面ボス</Place>
    <Level>Hard, Lunatic</Level>
  </SpellCard>
  <SpellCard ID="41">
    <Name>奇術「エターナルミーク」</Name>
    <Enemy>十六夜咲夜</Enemy>
    <Place>6面道中</Place>
    <Level>Normal, Hard, Lunatic</Level>
  </SpellCard>
  <SpellCard ID="42">
    <Name>天罰「スターオブダビデ」</Name>
    <Enemy>レミリア・スカーレット</Enemy>
    <Place>6面ボス</Place>
    <Level>Normal</Level>
  </SpellCard>
  <SpellCard ID="43">
    <Name>冥符「紅色の冥界」</Name>
    <Enemy>レミリア・スカーレット</Enemy>
    <Place>6面ボス</Place>
    <Level>Normal</Level>
  </SpellCard>
  <SpellCard ID="44">
    <Name>呪詛「ブラド・ツェペシュの呪い」</Name>
    <Enemy>レミリア・スカーレット</Enemy>
    <Place>6面ボス</Place>
    <Level>Normal</Level>
  </SpellCard>
  <SpellCard ID="45">
    <Name>紅符「スカーレットシュート」</Name>
    <Enemy>レミリア・スカーレット</Enemy>
    <Place>6面ボス</Place>
    <Level>Normal</Level>
  </SpellCard>
  <SpellCard ID="46">
    <Name>「レッドマジック」</Name>
    <Enemy>レミリア・スカーレット</Enemy>
    <Place>6面ボス</Place>
    <Level>Normal</Level>
  </SpellCard>
  <SpellCard ID="47">
    <Name>神罰「幼きデーモンロード」</Name>
    <Enemy>レミリア・スカーレット</Enemy>
    <Place>6面ボス</Place>
    <Level>Hard, Lunatic</Level>
  </SpellCard>
  <SpellCard ID="48">
    <Name>獄符「千本の針の山」</Name>
    <Enemy>レミリア・スカーレット</Enemy>
    <Place>6面ボス</Place>
    <Level>Hard, Lunatic</Level>
  </SpellCard>
  <SpellCard ID="49">
    <Name>神術「吸血鬼幻想」</Name>
    <Enemy>レミリア・スカーレット</Enemy>
    <Place>6面ボス</Place>
    <Level>Hard, Lunatic</Level>
  </SpellCard>
  <SpellCard ID="50">
    <Name>紅符「スカーレットマイスタ」</Name>
    <Enemy>レミリア・スカーレット</Enemy>
    <Place>6面ボス</Place>
    <Level>Hard, Lunatic</Level>
  </SpellCard>
  <SpellCard ID="51">
    <Name>「紅色の幻想郷」</Name>
    <Enemy>レミリア・スカーレット</Enemy>
    <Place>6面ボス</Place>
    <Level>Hard, Lunatic</Level>
  </SpellCard>
  <SpellCard ID="52">
    <Name>月符「サイレントセレナ」</Name>
    <Enemy>パチュリー・ノーレッジ</Enemy>
    <Place>EXTRA道中</Place>
    <Level>Extra</Level>
  </SpellCard>
  <SpellCard ID="53">
    <Name>日符「ロイヤルフレア」</Name>
    <Enemy>パチュリー・ノーレッジ</Enemy>
    <Place>EXTRA道中</Place>
    <Level>Extra</Level>
  </SpellCard>
  <SpellCard ID="54">
    <Name>火水木金土符「賢者の石」</Name>
    <Enemy>パチュリー・ノーレッジ</Enemy>
    <Place>EXTRA道中</Place>
    <Level>Extra</Level>
  </SpellCard>
  <SpellCard ID="55">
    <Name>禁忌「クランベリートラップ」</Name>
    <Enemy>フランドール・スカーレット</Enemy>
    <Place>EXTRAボス</Place>
    <Level>Extra</Level>
  </SpellCard>
  <SpellCard ID="56">
    <Name>禁忌「レーヴァテイン」</Name>
    <Enemy>フランドール・スカーレット</Enemy>
    <Place>EXTRAボス</Place>
    <Level>Extra</Level>
  </SpellCard>
  <SpellCard ID="57">
    <Name>禁忌「フォーオブアカインド」</Name>
    <Enemy>フランドール・スカーレット</Enemy>
    <Place>EXTRAボス</Place>
    <Level>Extra</Level>
  </SpellCard>
  <SpellCard ID="58">
    <Name>禁忌「カゴメカゴメ」</Name>
    <Enemy>フランドール・スカーレット</Enemy>
    <Place>EXTRAボス</Place>
    <Level>Extra</Level>
  </SpellCard>
  <SpellCard ID="59">
    <Name>禁忌「恋の迷路」</Name>
    <Enemy>フランドール・スカーレット</Enemy>
    <Place>EXTRAボス</Place>
    <Level>Extra</Level>
  </SpellCard>
  <SpellCard ID="60">
    <Name>禁弾「スターボウブレイク」</Name>
    <Enemy>フランドール・スカーレット</Enemy>
    <Place>EXTRAボス</Place>
    <Level>Extra</Level>
  </SpellCard>
  <SpellCard ID="61">
    <Name>禁弾「カタディオプトリック」</Name>
    <Enemy>フランドール・スカーレット</Enemy>
    <Place>EXTRAボス</Place>
    <Level>Extra</Level>
  </SpellCard>
  <SpellCard ID="62">
    <Name>禁弾「過去を刻む時計」</Name>
    <Enemy>フランドール・スカーレット</Enemy>
    <Place>EXTRAボス</Place>
    <Level>Extra</Level>
  </SpellCard>
  <SpellCard ID="63">
    <Name>秘弾「そして誰もいなくなるか？」</Name>
    <Enemy>フランドール・スカーレット</Enemy>
    <Place>EXTRAボス</Place>
    <Level>Extra</Level>
  </SpellCard>
  <SpellCard ID="64">
    <Name>ＱＥＤ「４９５年の波紋」</Name>
    <Enemy>フランドール・スカーレット</Enemy>
    <Place>EXTRAボス</Place>
    <Level>Extra</Level>
  </SpellCard>
</Th06SpellCardData>